traceai_autogen/__init__.py
traceai_autogen/utils.py
traceai_autogen/version.py
traceai_autogen-0.1.4.dist-info/METADATA
traceai_autogen-0.1.4.dist-info/WHEEL
traceai_autogen-0.1.4.dist-info/RECORD
